langgraph/prebuilt/__init__.py
langgraph/prebuilt/chat_agent_executor.py
langgraph/prebuilt/interrupt.py
langgraph/prebuilt/py.typed
langgraph/prebuilt/tool_node.py
langgraph/prebuilt/tool_validator.py
langgraph_prebuilt-1.0.3.dist-info/METADATA
langgraph_prebuilt-1.0.3.dist-info/WHEEL
langgraph_prebuilt-1.0.3.dist-info/licenses/LICENSE
langgraph_prebuilt-1.0.3.dist-info/RECORD
