Metadata-Version: 2.4
Name: langgraph-prebuilt
Version: 1.0.3
Summary: Library with high-level APIs for creating and executing LangGraph agents and tools.
Project-URL: Source, https://github.com/langchain-ai/langgraph/tree/main/libs/prebuilt
Project-URL: Twitter, https://x.com/LangChainAI
Project-URL: Slack, https://www.langchain.com/join-community
Project-URL: Reddit, https://www.reddit.com/r/LangChain/
License-Expression: MIT
License-File: LICENSE
Classifier: Development Status :: 5 - Production/Stable
Classifier: Programming Language :: Python
Classifier: Programming Language :: Python :: 3
Classifier: Programming Language :: Python :: 3 :: Only
Classifier: Programming Language :: Python :: 3.10
Classifier: Programming Language :: Python :: 3.11
Classifier: Programming Language :: Python :: 3.12
Classifier: Programming Language :: Python :: 3.13
Classifier: Programming Language :: Python :: Implementation :: CPython
Classifier: Programming Language :: Python :: Implementation :: PyPy
Requires-Python: >=3.10
Requires-Dist: langchain-core>=1.0.0
Requires-Dist: langgraph-checkpoint<4.0.0,>=2.1.0
